{
    "Phoenix":     { "tracer": true, "fastmap": true, "spilkpk": true, "carejector": true, "quickmap": true },
    "Tucson":      { "tracer": false, "fastmap": false, "spilkpk": false, "carejector": false, "quickmap": false },
    "Scottdale":   { "tracer": false, "fastmap": false, "spilkpk": false, "carejector": false, "quickmap": false },
    "Chandler":    { "tracer": false, "fastmap": false, "spilkpk": false, "carejector": false, "quickmap": false },
    "Brainburg":   { "tracer": true,  "fastmap": false, "spilkpk": false, "carejector": false, "quickmap": false },
    "Saint Rose":  { "tracer": false, "fastmap": false, "spilkpk": false, "carejector": false, "quickmap": false },
    "Mesa":        { "tracer": false, "fastmap": false, "spilkpk": false, "carejector": false, "quickmap": false },
    "Red-Rock":    { "tracer": false, "fastmap": false, "spilkpk": false, "carejector": false, "quickmap": false },
    "Yuma":        { "tracer": false, "fastmap": false, "spilkpk": false, "carejector": false, "quickmap": false },
    "Surprise":    { "tracer": false, "fastmap": true,  "spilkpk": false, "carejector": false, "quickmap": false },
    "Prescott":    { "tracer": false, "fastmap": false, "spilkpk": false, "carejector": false, "quickmap": false },
    "Glendale":    { "tracer": true,  "fastmap": true,  "spilkpk": true,  "carejector": true,  "quickmap": true  },
    "Kingman":     { "tracer": false, "fastmap": false, "spilkpk": false, "carejector": false, "quickmap": false },
    "Winslow":     { "tracer": false, "fastmap": false, "spilkpk": false, "carejector": false, "quickmap": false },
    "Payson":      { "tracer": false, "fastmap": false, "spilkpk": false, "carejector": false, "quickmap": false },
    "Gilbert":     { "tracer": false, "fastmap": false, "spilkpk": false, "carejector": false, "quickmap": false },
    "Show Low":    { "tracer": false, "fastmap": false, "spilkpk": false, "carejector": false, "quickmap": false },
    "Casa-Grande": { "tracer": false, "fastmap": false, "spilkpk": false, "carejector": false, "quickmap": false },
    "Page":        { "tracer": false, "fastmap": false, "spilkpk": false, "carejector": false, "quickmap": false },
    "Sun-City":    { "tracer": false, "fastmap": false, "spilkpk": false, "carejector": false, "quickmap": false },
    "Queen-Creek": { "tracer": false, "fastmap": false, "spilkpk": false, "carejector": false, "quickmap": false },
    "Sedona":      { "tracer": false, "fastmap": false, "spilkpk": false, "carejector": false, "quickmap": false },
    "Holiday":     { "tracer": false, "fastmap": false, "spilkpk": false, "carejector": false, "quickmap": false },
    "Wednesday":   { "tracer": false, "fastmap": false, "spilkpk": false, "carejector": false, "quickmap": false },
    "Yava":        { "tracer": false, "fastmap": false, "spilkpk": false, "carejector": false, "quickmap": false },
    "Faraway":     { "tracer": false, "fastmap": false, "spilkpk": false, "carejector": false, "quickmap": false },
    "Bumble Bee":  { "tracer": false, "fastmap": false, "spilkpk": false, "carejector": false, "quickmap": false },
    "Christmas":   { "tracer": false, "fastmap": false, "spilkpk": false, "carejector": false, "quickmap": false },
    "Mirage":      { "tracer": false, "fastmap": false, "spilkpk": false, "carejector": false, "quickmap": false },
    "Love":        { "tracer": false, "fastmap": false, "spilkpk": false, "carejector": false, "quickmap": false },
    "Drake":       { "tracer": false, "fastmap": false, "spilkpk": false, "carejector": false, "quickmap": false },
    "Space":       { "tracer": true,  "fastmap": true,  "spilkpk": true,  "carejector": true,  "quickmap": true  }
}
